StrDiffSynch/LRUCache.py
StrDiffSynch/RemoteStrSynch.py
StrDiffSynch/StrDiffSynch.py
StrDiffSynch/__init__.py
StrDiffSynch-2.2.6.dist-info/LICENSE
StrDiffSynch-2.2.6.dist-info/METADATA
StrDiffSynch-2.2.6.dist-info/WHEEL
StrDiffSynch-2.2.6.dist-info/top_level.txt
StrDiffSynch-2.2.6.dist-info/RECORD
