Metadata-Version: 2.1
Name: StrDiffSynch
Version: 2.2.6
Summary: This module calculates the difference from one string to another. If the origin string absorbs the difference, it becomes the other string. Thus, two endpoints could synchronize the strings by passing the difference.
Home-page: https://github.com/monk-after-90s/StrDiffSynch.git
Author: Antas
License: MIT
Platform: UNKNOWN
Classifier: Programming Language :: Python :: 3
Classifier: License :: OSI Approved :: MIT License
Classifier: Operating System :: OS Independent
Requires-Python: >=3.7
License-File: LICENSE
